lektor_google_analytics.py
lektor_google_analytics-0.1.3.dist-info/DESCRIPTION.rst
lektor_google_analytics-0.1.3.dist-info/METADATA
lektor_google_analytics-0.1.3.dist-info/RECORD
lektor_google_analytics-0.1.3.dist-info/WHEEL
lektor_google_analytics-0.1.3.dist-info/entry_points.txt
lektor_google_analytics-0.1.3.dist-info/metadata.json
lektor_google_analytics-0.1.3.dist-info/top_level.txt
