Metadata-Version: 2.0
Name: lektor-google-analytics
Version: 0.1.3
Summary: Adds support for Google analytics to Lektor CMS
Home-page: http://github.com/kmonsoor/lektor-google-analytics
Author: Khaled Monsoor
Author-email: k@kmonsoor.com
License: BSD
Platform: UNKNOWN
Classifier: Development Status :: 3 - Alpha
Classifier: Environment :: Console
Classifier: License :: OSI Approved :: BSD License
Classifier: Operating System :: OS Independent
Classifier: Programming Language :: Python :: 2
Classifier: Programming Language :: Python :: 2.7
Classifier: Topic :: Internet :: WWW/HTTP
Classifier: Topic :: Software Development :: Libraries :: Python Modules
Requires: lektor
